lazy_fred.py
lazy_fred-0.1.65.dist-info/LICENSE
lazy_fred-0.1.65.dist-info/METADATA
lazy_fred-0.1.65.dist-info/WHEEL
lazy_fred-0.1.65.dist-info/RECORD
