Metadata-Version: 2.1
Name: lazy_fred
Version: 0.1.65
Summary: 'A simplified aggegate of FRED data using fredapi package'
License: MIT
Author: Jmetrics86
Author-email: jsnbrwstr@gmail.com
Requires-Python: >=3.10,<4.0
Classifier: License :: OSI Approved :: MIT License
Classifier: Programming Language :: Python :: 3
Classifier: Programming Language :: Python :: 3.10
Classifier: Programming Language :: Python :: 3.11
Classifier: Programming Language :: Python :: 3.12
Requires-Dist: fred (>=3.1,<4.0)
Requires-Dist: fredapi (>=0.5.2,<0.6.0)
Requires-Dist: pandas (>=2.0.2,<3.0.0)
Requires-Dist: python-dotenv (>=1.0.1,<2.0.0)
